Workbook

Sheet README
B2: Kleros AI Benchmark — Model-Version Verdict Tracker
B3: Lemon Cash disputes · Schelling-point juror assessment · 99-case panel
B5: What this benchmark measures
B6: This workbook turns a fixed, hand-curated corpus of 99 real Kleros 'Lemon' disputes into a regression benchmark for Claude model versions. Each model version assesses the SAME 99 cases as a diligent Kleros juror (verdict = Rule for Lemon / Rule for the User, plus a confidence level). The benchmark tracks, version over version: (1) how the verdict distribution shifts, (2) the case-by-case agreement rate, (3) which specific cases flip and in which direction, and (4) confidence calibration. The aim is to detect and characterise behavioural drift as models are upgraded — not (yet) to score against a legal ground truth.
B8: Sheets in this workbook
B9: • Dashboard — Headline metrics + chart: verdict split per version, agreement rate, flip count & direction, confidence mix. All formula-driven from 'Case Matrix'.
B10: • Case Matrix — One row per case (99). Fixed metadata columns, then a {Verdict, Confidence} block per model version. Agreement & flip-direction computed by formula.
B11: • Flip Log — The 11 cases whose verdict changed between v4.7 and v4.8, with each model's reasoning, the change driver, and a high-confidence-reversal flag.
B12: • Change Drivers — The five recurring mechanisms behind the v4.7→v4.8 flips, with definitions and case counts.
B14: How to add the next model version (e.g. v4.9 / v5.0)
B15: 1. Re-run the same 99 cases through the new model with the identical Kleros juror skill/prompt and the same inputs. 2. In 'Case Matrix', insert two new columns immediately to the LEFT of the 'Agree?' column: '<ver> Verdict' and '<ver> Confidence'. Paste the new verdicts (use exactly the tokens 'Lemon' / 'User'). 3. Repoint the 'Agree?' and 'Flip' formulas to compare the new version against the previous one (the template compares the two newest blocks). 4. On 'Dashboard', copy the v4.8 metric column, point its COUNTIF ranges at the new columns, and extend the chart data range. 5. Log any new flips on 'Flip Log' and tag each with a Change Driver.
B17: Scoring conventions & caveats
... B20: Generated by Claude (v4.8) · comparison baseline: Claude v4.7 Opus (Adaptive Thinking)

Sheet Dashboard
B2: Kleros AI Benchmark — Dashboard
B3: Claude v4.7 Opus → v4.8 Max Thinking · 99 Lemon disputes
B5: Cases compared | D5: Agreement rate | F5: Verdicts flipped
B6: =COUNT('Case Matrix'!A:A) -> 99 | D6: =COUNTIF('Case Matrix'!I:I,"Agree")/COUNT('Case Matrix'!A:A) -> 0.88888889 | F6: =COUNTIF('Case Matrix'!I:I,"FLIP") -> 11
B7: identical case set | D7: verdict consistency | F7: of 99 cases
B9: Flips: User→Lemon | D9: Flips: Lemon→User | F9: High-conf. reversals
B10: =COUNTIF('Case Matrix'!J:J,"User→Lemon") -> 10 | D10: =COUNTIF('Case Matrix'!J:J,"Lemon→User") -> 1 | F10: =COUNTIFS('Case Matrix'!F:F,"High",'Case Matrix'!I:I,"FLIP") -> 2
B11: more pro-platform | D11: more pro-consumer | F11: v4.7 was 'High'
B14: Verdict distribution
B15: Outcome | C15: v4.7 | D15: v4.8 | E15: Δ (4.8−4.7)
B16: Rule for Lemon | C16: =COUNTIF('Case Matrix'!E:E,"Lemon") -> 85 | D16: =COUNTIF('Case Matrix'!G:G,"Lemon") -> 94 | E16: =D16-C16 -> 9
B17: Rule for the User | C17: =COUNTIF('Case Matrix'!E:E,"User") -> 14 | D17: =COUNTIF('Case Matrix'!G:G,"User") -> 5 | E17: =D17-C17 -> -9
B18: Total | C18: =SUM(C16:C17) -> 99 | D18: =SUM(D16:D17) -> 99
B21: Confidence mix
B22: Confidence | C22: v4.7 | D22: v4.8
B23: High | C23: =COUNTIF('Case Matrix'!F:F,"High") -> 72 | D23: =COUNTIF('Case Matrix'!H:H,"High") -> 68
B24: Medium | C24: =COUNTIF('Case Matrix'!F:F,"Medium") -> 25 | D24: =COUNTIF('Case Matrix'!H:H,"Medium") -> 31
B25: Medium-High | C25: =COUNTIF('Case Matrix'!F:F,"Medium-High") -> 2 | D25: =COUNTIF('Case Matrix'!H:H,"Medium-High") -> 0

Sheet Case Matrix
A1: Case Matrix — per-case verdicts by model version
A2: Fixed metadata on the left; one {Verdict, Confidence} block per version. Add new versions before the 'Agree?' column.
A4: Case # | B4: Category | C4: Amount in dispute | D4: Product / issue | E4: v4.7 Verdict | F4: v4.7 Conf. | G4: v4.8 Verdict | H4: v4.8 Conf. | I4: Agree? | J4: Flip (prev→new)
A5: 4 | B5: Unauthorized / disputed card charge | C5: USD 218 (converted to ARS 104,781) — transferred to third-pa | D5: Account security / unauthorised transfers following pho | E5: Lemon | F5: Medium | G5: User | H5: Medium | I5: =IF($E5=$G5,"Agree","FLIP") -> FLIP | J5: =IF($E5=$G5,"—",$E5&"→"&$G5) -> Lemon→User
A6: 5 | B6: Commission / fee / valuation | C6: ARS 3,525.15 (Tinder charge dated 27/04/2023 01:38–01:39hs) | D6: Lemon Cash prepaid VISA card — disputed Tinder charge | E6: Lemon | F6: Medium | G6: Lemon | H6: Medium | I6: =IF($E6=$G6,"Agree","FLIP") -> Agree | J6: =IF($E6=$G6,"—",$E6&"→"&$G6) -> —
A7: 6 | B7: Unlisted token / wrong network (crypto) | C7: ~USD 1–2 (15,000 LUNC tokens converted to ~1 USDC); user inv | D7: Delisting / forced conversion of LUNC (Luna Classic) an | E7: Lemon | F7: High | G7: Lemon | H7: High | I7: =IF($E7=$G7,"Agree","FLIP") -> Agree | J7: =IF($E7=$G7,"—",$E7&"→"&$G7) -> —
A8: 7 | B8: Scam / third-party fraud | C8: 250 USDC | D8: Depósito accidental de USDC en la red Optimism (red no | E8: User | F8: Medium | G8: Lemon | H8: Medium | I8: =IF($E8=$G8,"Agree","FLIP") -> FLIP | J8: =IF($E8=$G8,"—",$E8&"→"&$G8) -> User→Lemon
A9: 8 | B9: Scam / third-party fraud | C9: ~USD 72.68 (per user's app screenshot showing -$72.68 moveme | D9: Crypto deposit (Ethereum/WETH) sent over the Optimism n | E9: Lemon | F9: Medium | G9: Lemon | H9: Medium | I9: =IF($E9=$G9,"Agree","FLIP") -> Agree | J9: =IF($E9=$G9,"—",$E9&"→"&$G9) -> —
A10: 9 | B10: Promotion / cashback / referral | C10: User claims 180 USD; Lemon disputes the figure as not matchi | D10: "Reintegro Pagos de Servicios" — Oct 2023 promotion off | E10: Lemon | F10: Medium | G10: Lemon | H10: Medium | I10: =IF($E10=$G10,"Agree","FLIP") -> Agree | J10: =IF($E10=$G10,"—",$E10&"→"&$G10) -> —
A11: 10 | B11: Promotion / cashback / referral | C11: 50% reintegro on a 4th utility-bill payment, capped at AR$1, | D11: "Reintegro Pagos de Servicios" — Lemon promotion (02–13 | E11: User | F11: High | G11: User | H11: High | I11: =IF($E11=$G11,"Agree","FLIP") -> Agree | J11: =IF($E11=$G11,"—",$E11&"→"&$G11) -> —
A12: 11 | B12: Commission / fee / valuation | C12: ARS 15,493.67 (user states ARS 15,500) — card purchase to "D | D12: Lemon Cash debit-card transaction / chargeback (compra | E12: User | F12: Medium | G12: Lemon | H12: Medium | I12: =IF($E12=$G12,"Agree","FLIP") -> FLIP | J12: =IF($E12=$G12,"—",$E12&"→"&$G12) -> User→Lemon
A13: 12 | B13: Unauthorized / disputed card charge | C13: ARS 40,000 (three transactions at MERPAGO*TICKETPASS on 13/1 | D13: Lemon Cash prepaid card — disputed/unauthorized transac | E13: Lemon | F13: High | G13: Lemon | H13: Medium | I13: =IF($E13=$G13,"Agree","FLIP") -> Agree | J13: =IF($E13=$G13,"—",$E13&"→"&$G13) -> —
A14: 13 | B14: Promotion / cashback / referral | C14: User claims approximately $9,000 (pesos) reintegro; Lemon sa | D14: "Reintegro Pagos de Servicios" — 50% reintegro on first | E14: Lemon | F14: High | G14: Lemon | H14: Medium | I14: =IF($E14=$G14,"Agree","FLIP") -> Agree | J14: =IF($E14=$G14,"—",$E14&"→"&$G14) -> —
A15: 15 | B15: Unauthorized / disputed card charge | C15: ARS 12,924.02 (purchase 6,619.66 + taxes 6,304.36) — 22 Nove | D15: Chargeback / reversal of a card transaction on Lemon Ca | E15: Lemon | F15: High | G15: Lemon | H15: High | I15: =IF($E15=$G15,"Agree","FLIP") -> Agree | J15: =IF($E15=$G15,"—",$E15&"→"&$G15) -> —
A16: 17 | B16: Unlisted token / wrong network (crypto) | C16: ~400 UXD (approx. USD 400) | D16: Cash-In of UXD (Ripio's stablecoin) from Ripio to a Lem | E16: Lemon | F16: High | G16: Lemon | H16: High | I16: =IF($E16=$G16,"Agree","FLIP") -> Agree | J16: =IF($E16=$G16,"—",$E16&"→"&$G16) -> —
... A103: 122 | B103: Wrong address/alias transfer (user error) | C103: ARS 110.000 | D103: ARS withdrawal (Retiro de ARS) via Lemon — CBU transfer | E103: Lemon | F103: High | G103: Lemon | H103: High | I103: =IF($E103=$G103,"Agree","FLIP") -> Agree | J103: =IF($E103=$G103,"—",$E103&"→"&$G103) -> —

Sheet Flip Log
A1: Flip Log — the 11 cases that changed verdict (v4.7 → v4.8)
A2: 10 moved toward the platform (User→Lemon); 1 moved toward the consumer (Lemon→User). Two reversed a 'High'-confidence v4.7 verdict.
A4: Case | B4: Category | C4: Amount | D4: v4.7 | E4: Conf. | F4: v4.8 | G4: Conf. | H4: Direction | I4: Why v4.7 ruled this way | J4: Why v4.8 ruled this way | K4: Driver(s) | L4: High-conf. reversal?
A5: 4 | B5: Unauthorized card charge | C5: USD 218 | D5: Lemon | E5: Medium | F5: User | G5: Medium | H5: Lemon→User | I5: Put the burden on the user to show Lemon's security perimeter failed; the login log (same stolen Device ID, valid credentials re-entered after the 5-min timeout) placed the breach at the user's own credential layer, so Protección / in dubio could not reallocate the loss. | J5: Read the SAME device-ID log as corroborating the documented street-theft (~39 min earlier); Lemon's 'must have been phished' theory was speculative and unproven, so genuine doubt resolved pro consumidor for the user. | K5: D4, D5 | L5: No — lone pro-consumer flip
A6: 7 | B6: Wrong-network deposit | C6: 250 USDC | D6: User | E6: Medium | F6: Lemon | G6: Medium | H6: User→Lemon | I6: Unrebutted on-chain trail showed funds reached a Lemon-controlled address then moved to Binance; Lemon's own admission it was 'working with the provider to refund' showed recovery was feasible and contradicted its no-access defence. | J6: Explorer screenshots show only truncated '0x' fields — 'Lemon has access' is unproven; the user conceded the T&C disclosed unsupported-network risk, so the loss flows from his own authorised act and 'industry custom' can't override disclosed terms. | K6: D1, D3, D5 | L6: No
A7: 11 | B7: Disputed merchant charge | C7: ARS 15,494 | D7: User | E7: Medium | F7: Lemon | G7: Medium | H7: User→Lemon | I7: Two unrebutted Hostinger/dLocal emails ('no record of the payment') shifted the burden to Lemon, which offered only behavioural proxies (prior merchant use, same-day cashback) and no settlement or authentication record. | J7: The processor 'no record / ask your bank' reply is a routine deflection, not proof of fraud; Lemon's unrebutted prior-merchant history plus the user's own same-day cashback conversion evidence account control, so no Lemon failure is shown. | K7: D1, D5 | L7: No
A8: 25 | B8: Card-not-present (Xsolla) | C8: ~USD 60 | D8: User | E8: High | F8: Lemon | G8: Medium | H8: User→Lemon | I8: Strong prima facie fraud — card dormant since 2022, the 2020 Xsolla receipt used a different method (the Lemon card didn't yet exist), making Lemon's 'you already gave Xsolla the data' factually wrong; Lemon produced no 3DS / PIN / IP evidence. | J8: Agrees Lemon's specific argument is weak, but holds a weak defence does not discharge the USER's burden — a card-not-present charge to a real processor shows third-party data compromise, not a demonstrated Lemon security failure; a factual dispute does not trigger in dubio. | K8: D1, D4 | L8: YES — v4.7 was High
A9: 27 | B9: Card-not-present (ABL tax) | C9: ARS 7,172 | D9: User | E9: Medium | F9: Lemon | G9: Medium | H9: User→Lemon | I9: Credited a coherent, document-supported denial (Chaco resident vs a Buenos Aires city tax, corroborated by a third-party statement); Lemon, best placed to produce device/IP/3DS data, produced none. | J9: Residence proves nothing about a Lemon failure — card-not-present fraud is location-independent; the controversy is factual not a term ambiguity, so in dubio isn't engaged and no Lemon breach is proven. | K9: D1, D4, D5 | L9: No
A10: 56 | B10: Unlisted-asset withdrawal | C10: ~USD 30 | D10: User | E10: Medium | F10: Lemon | G10: High | H10: User→Lemon | I10: Lemon's own UI screen titled 'Retiro de Ethereum' with an ETH icon and 'Con éxito' but a WETH quantity was internally inconsistent and misleading; T&C 13.7 (unlisted-asset immunity) could not override the Información / Transparencia duties. | J10: The user's own screenshot shows a successful, user-authorised, irreversible withdrawal; 13.7 is a legitimate limit consistent with the policy (an exchange can't reflect a token it doesn't list) and Lemon met its info/education duties — the loss is the user's own act. | K10: D1, D2, D3 | L10: No (v4.8 raised conf. to High)
A11: 80 | B11: Unlisted token (GRASS) | C11: ~USD 32 | D11: User | E11: Medium | F11: Lemon | G11: Medium | H11: User→Lemon | I11: Lemon's own published FAQ (recovery for non-ERC20 networks from USD 1 at 10%) was the binding 'offer as presented'; Lemon had to apply it or prove case-specific technical impossibility, which it never did. | J11: The FAQ is expressly conditional ('we review whether it can be recovered … if we can recover them'), not a promise; GRASS is undisputedly unlisted so T&C 13.7 applies, and support had already told the user it was unrecoverable — no genuine ambiguity. | K11: D3, D2, D1 | L11: No
A12: 81 | B12: Unlisted token (GRASS) | C12: ~USD 80 | D12: User | E12: Medium | F12: Lemon | G12: Medium | H12: User→Lemon | I12: Same FAQ-as-offer logic as Case 80, reinforced by Lemon listing BSOL (proof it already operates the Solana network), so a blanket impossibility defence failed; the 13.7 catch-all couldn't override Section A. | J12: Materially identical to Case 80 — the conditional FAQ is no promise, 13.7 governs the unlisted token, the user over-read an explicit condition; in dubio is not triggered. | K12: D3, D2, D1 | L12: No
A13: 85 | B13: Migration delay / valuation | C13: USD 28 | D13: User | E13: Medium | F13: Lemon | G13: High | H13: User→Lemon | I13: Parsed Lemon's 9 Jan email as two distinct promises and found the dated 14/01 conversion was breached (credited only on 20/01, six days late); the breach was established even though quantum was speculative. | J13: The email disclosed BOTH the ~14/01 conversion and that functions 'may be limited for a few days', so the risk was disclosed up front; the migration was 1:1, the loss is an unrealised theoretical gain, and the user conceded the message 'fue claro'. | K13: D3, D1 | L13: No (v4.8 raised conf. to High)
A14: 100 | B14: Duplicate transfer (Yape) | C14: S/ 100 | D14: User | E14: Medium | F14: Lemon | G14: Medium | H14: User→Lemon | I14: The two debits shared identical metadata — same recipient, CCI, phone and the SAME free-text message 48 seconds apart — the signature of one retried transfer after a UI error, which Lemon never rebutted point-by-point. | J14: The two cash-outs carry distinct operation numbers and transaction IDs to the same valid CCI — hallmarks of two separately-authorised transfers, not a system duplicate; whether the payee received the second is a downstream Yape matter. | K14: D5, D1 | L14: No
A15: 117 | B15: Transfer not credited | C15: PEN 50 | D15: User | E15: High | F15: Lemon | G15: Medium | H15: User→Lemon | I15: Lemon's own 'Constancia de envío' success voucher is a certification of a completed act; its ~2-month-later 'no se realizó' retraction, with no explanation or remediation and an unexplained operation-ID digit discrepancy, was a textbook transparency violation. | J15: Both the user's voucher AND Lemon's back-office panel show 'Completada' to the exact intended recipient/CCI; the pivotal 'no se realizó' notice was never put in evidence by either side, so the asserted Lemon failure is unproven — decide on the record. | K15: D1, D5 | L15: YES — v4.7 was High

Sheet Change Drivers
A1: Change Drivers — the mechanisms behind the v4.7 → v4.8 flips
A2: Drivers overlap: a single flip usually combines two or three. Counts = flips where that mechanism was operative.
A4: Code | B4: Mechanism | C4: Definition | D4: Flips | E4: Cases
A5: D1 | B5: Burden of proof relocated to the claimant | C5: v4.8 requires the user to affirmatively prove a Lemon-side breach; a weak or thin platform defence is no longer enough to hand the user the win. v4.7 instead shifted the burden onto Lemon once the user made a coherent prima facie showing. | D5: 10 | E5: 7, 11, 25, 27, 56, 80, 81, 85, 100, 117
A6: D2 | B6: T&C clause read as policy-consistent, not overridden | C6: v4.8 treats clauses such as 13.7 (unlisted assets) and 5.1/5.2 (chargeback routing) as legitimate operational limits consistent with the policy. v4.7 routinely applied a 'Sección B: a catch-all immunity cannot override Sección A' move to set such clauses aside. | D6: 3 | E6: 56, 80, 81
A7: D3 | B7: 'As-presented' offer read literally / conditionally | C7: Vouchers, FAQs and announcement emails that v4.7 treated as binding 'offer-as-presented' promises, v4.8 reads as conditional, already-disclosed, or not a promise at all (e.g. a FAQ saying 'if we can recover them'). | D7: 5 | E7: 7, 56, 80, 81, 85
A8: D4 | B8: in dubio pro consumidor confined to genuine textual ambiguity | C8: v4.8 reserves the pro-consumer tiebreaker for genuine ambiguity in the TERMS and declines to apply it to FACTUAL disputes (was it fraud? was it a duplicate?). v4.7 used it more readily as a reinforcing tiebreaker. (In Case 4 the stricter test cut the other way and favoured the consumer.) | D8: 3 | E8: 4, 25, 27
A9: D5 | B9: Pivotal evidence reweighted | C9: The same exhibit is read to the opposite conclusion — e.g. a device-ID log as theft-corroboration vs user-fault (4); identical transfer metadata as a duplicate vs two distinct authorised cash-outs (100); a processor 'no record' email as proof of fraud vs routine deflection (11). | D9: 6 | E9: 4, 7, 11, 27, 100, 117
A11: Headline: in all 10 cases that moved toward the platform, the operative change is D1 — v4.8 holds the claimant to a strict burden of proof and will not convert a weak Lemon defence into a consumer win. The single consumer-ward flip (Case 4) comes from the same rigour applied to Lemon's unproven exculpatory theory.
